{
  "todos": [
    {
      "id": "1737105962299",
      "title": "Build a Todo App",
      "completed": true
    },
    {
      "id": "1737105962300",
      "title": "Study Redux",
      "completed": true
    },
    {
      "id": "1737105962301",
      "title": "Practice JavaScript",
      "completed": false
    },
    {
      "id": "1737105962303",
      "title": "Write unit tests",
      "completed": false
    },
    {
      "id": "1737105962305",
      "title": "Build a portfolio website",
      "completed": false
    },
    {
      "id": "1737105962306",
      "title": "Create a React project",
      "completed": true
    },
    {
      "id": "1737105962308",
      "title": "Explore Next.js",
      "completed": false
    }
  ]
}